odoo8_addon_hr_expense_move_date-8.0.1.0.0.99.dev7-py2.7-nspkg.pth
odoo8_addon_hr_expense_move_date-8.0.1.0.0.99.dev7.dist-info/DESCRIPTION.rst
odoo8_addon_hr_expense_move_date-8.0.1.0.0.99.dev7.dist-info/METADATA
odoo8_addon_hr_expense_move_date-8.0.1.0.0.99.dev7.dist-info/RECORD
odoo8_addon_hr_expense_move_date-8.0.1.0.0.99.dev7.dist-info/WHEEL
odoo8_addon_hr_expense_move_date-8.0.1.0.0.99.dev7.dist-info/metadata.json
odoo8_addon_hr_expense_move_date-8.0.1.0.0.99.dev7.dist-info/namespace_packages.txt
odoo8_addon_hr_expense_move_date-8.0.1.0.0.99.dev7.dist-info/top_level.txt
odoo_addons/hr_expense_move_date/README.rst
odoo_addons/hr_expense_move_date/__init__.py
odoo_addons/hr_expense_move_date/__openerp__.py
odoo_addons/hr_expense_move_date/i18n/de.po
odoo_addons/hr_expense_move_date/i18n/es.po
odoo_addons/hr_expense_move_date/i18n/fi.po
odoo_addons/hr_expense_move_date/i18n/fr.po
odoo_addons/hr_expense_move_date/i18n/hr_expense_move_date.pot
odoo_addons/hr_expense_move_date/i18n/pt_BR.po
odoo_addons/hr_expense_move_date/i18n/sl.po
odoo_addons/hr_expense_move_date/models/__init__.py
odoo_addons/hr_expense_move_date/models/hr_expense.py
odoo_addons/hr_expense_move_date/static/description/icon.png
odoo_addons/hr_expense_move_date/tests/__init__.py
odoo_addons/hr_expense_move_date/tests/test_hr_expense.py
odoo_addons/hr_expense_move_date/views/hr_expense_views.xml
